hmd_cli_bender/__init__.py
hmd_cli_bender/controller.py
hmd_cli_bender/hmd_cli_bender.py
hmd_cli_bender-0.1.31.dist-info/METADATA
hmd_cli_bender-0.1.31.dist-info/WHEEL
hmd_cli_bender-0.1.31.dist-info/top_level.txt
hmd_cli_bender-0.1.31.dist-info/RECORD
