Metadata-Version: 2.1
Name: hmd-cli-bender
Version: 0.1.31
Summary: CLI for bender transform
Home-page: UNKNOWN
Author: Kate Walls
Author-email: kate.walls@hmdlabs.io
License: Apache 2.0
Platform: UNKNOWN
Requires-Dist: aws-secretsmanager-caching (==1.1.1.5)
Requires-Dist: boto3 (==1.36.22)
Requires-Dist: botocore (==1.36.23)
Requires-Dist: cachetools (==5.2.0)
Requires-Dist: cement (==3.0.6)
Requires-Dist: certifi (==2022.12.7)
Requires-Dist: charset-normalizer (==2.0.12)
Requires-Dist: colorlog (==6.6.0)
Requires-Dist: google-auth (==2.9.1)
Requires-Dist: hmd-cli-app (~=1.2.603)
Requires-Dist: hmd-cli-tools (~=1.2.236)
Requires-Dist: idna (==3.3)
Requires-Dist: inquirerpy (==0.3.4)
Requires-Dist: jinja2 (==3.0.3)
Requires-Dist: jmespath (==0.10.0)
Requires-Dist: kubernetes (==24.2.0)
Requires-Dist: markupsafe (==3.0.2)
Requires-Dist: oauthlib (==3.2.2)
Requires-Dist: pfzy (==0.3.4)
Requires-Dist: prompt-toolkit (==3.0.38)
Requires-Dist: pyasn1 (==0.4.8)
Requires-Dist: pyasn1-modules (==0.2.8)
Requires-Dist: python-dateutil (==2.8.2)
Requires-Dist: python-dotenv (==0.19.2)
Requires-Dist: pyyaml (==6.0.1)
Requires-Dist: requests (==2.32.3)
Requires-Dist: requests-oauthlib (==1.3.1)
Requires-Dist: rsa (==4.8)
Requires-Dist: s3transfer (==0.11.2)
Requires-Dist: six (==1.16.0)
Requires-Dist: urllib3 (==1.26.8)
Requires-Dist: wcwidth (==0.2.6)
Requires-Dist: websocket-client (==1.3.3)
